{
  "continents": [
    {
      "nom": "Nordique",
      "flore": [
        {
          "type": "Normaux",
          "plantes": [
            {
              "nom": "Mousse glaciaire",
              "apparence": "Couche verte ou grise épaisse recouvrant les roches, texture spongieuse, jusqu'à 10 cm de haut.",
              "ressources_rares_sacrees": "Plante commune utilisée pour l’isolation, fibres absorbantes efficaces contre le froid.",
              "saison_floraison": "Persistante toute l’année, croissance lente en hiver, pic de pousse au dégel printanier.",
              "localisation_biome": "Vallées glaciaires et plateaux humides de Valléfrost et Grunthalok.",
              "usages_medicinaux": "Cataplasmes contre les gelures, infusions respiratoires.",
              "usages_artisanaux": "Isolation des habitations et rembourrage des parois.",
              "usages_rituels": "Brûlée par les trolls pour bénir les récoltes et apaiser l’esprit de l’hiver."
            },
            {
              "nom": "Arbre médicinal conifère",
              "apparence": "Grand conifère à aiguilles persistantes et écorce résineuse, hauteur 20 à 30 m, cônes bruns.",
              "ressources_rares_sacrees": "Résine aromatique utilisée pour potions et rituels.",
              "saison_floraison": "Pollen au printemps, cônes mûrs à l’automne, cycle de 2 à 3 ans.",
              "localisation_biome": "Forêts humides et steppes acides de Grunthalok et Varkhul.",
              "usages_medicinaux": "Résine antiseptique pour pansements et décoctions purifiantes.",
              "usages_artisanaux": "Bois dur et stable utilisé pour totems et outils rituels.",
              "usages_rituels": "Résine brûlée dans les rituels chamaniques des trolls de Grunthalok."
            },
            {
              "nom": "Lichen stellaire",
              "apparence": "Mousse argentée luminescente adhérant aux pierres, brille légèrement la nuit.",
              "ressources_rares_sacrees": "Plante semi-sacrée, indicateur de pureté magique.",
              "saison_floraison": "Active uniquement durant les nuits de pleine lune.",
              "localisation_biome": "Falaises de Slekdor et cavernes glaciaires.",
              "usages_medicinaux": "Tonique respiratoire et apaisant des nerfs.",
              "usages_artisanaux": "Teintures argentées pour symboles rituels.",
              "usages_rituels": "Utilisé dans les bénédictions astronomiques et méditations géantes."
            }
          ]
        },
        {
          "type": "Rares_sacrees",
          "plantes": [
            {
              "nom": "Herbe toxique steppique",
              "apparence": "Tiges jaunes et fleurs pourpres, 40 cm de haut, racines bulbeuses.",
              "ressources_rares_sacrees": "Source de soufre corrompu, sacrée pour les gobelins alchimistes.",
              "saison_floraison": "Brève floraison estivale suivant la fonte des neiges.",
              "localisation_biome": "Steppe maudite de Varkhul.",
              "usages_medicinaux": "Poisons dilués servant d’antidouleurs puissants.",
              "usages_artisanaux": "Teintures sombres pour cuir gobelin.",
              "usages_rituels": "Inhalée lors de rituels obscurs gobelins pour visions instables."
            },
            {
              "nom": "Fleur cristalline",
              "apparence": "Pétales translucides semblables à du quartz, tige courte enracinée dans la pierre.",
              "ressources_rares_sacrees": "Cristaux cosmiques, symboles de sagesse géante.",
              "saison_floraison": "Solstice d’été, cycle de floraison de 5 ans.",
              "localisation_biome": "Sommets isolés de Slekdor, au-delà de 3000 m.",
              "usages_medicinaux": "Élixirs de concentration et visions astrales.",
              "usages_artisanaux": "Ornementation d’artefacts et d’amulettes.",
              "usages_rituels": "Brûlée lors de méditations cosmiques des géants."
            }
          ]
        }
      ]
    },
    {
      "nom": "Central",
      "flore": [
        {
          "type": "Normaux",
          "plantes": [
            {
              "nom": "Herbe fertile de plaine",
              "apparence": "Tiges vertes et épis dorés, 1 mètre de haut, racines profondes.",
              "ressources_rares_sacrees": "Céréale de base, abondante et nourricière.",
              "saison_floraison": "Printemps à été, récolte en automne.",
              "localisation_biome": "Plaines fertiles de Dralvaire.",
              "usages_medicinaux": "Infusions digestives légères.",
              "usages_artisanaux": "Paille utilisée pour tressage et stockage.",
              "usages_rituels": "Offrande de fertilité brûlée à la moisson."
            },
            {
              "nom": "Roseau marécageux",
              "apparence": "Tiges hautes creuses et plumeuses, 3 m en moyenne.",
              "ressources_rares_sacrees": "Fibres résistantes des marais.",
              "saison_floraison": "Été humide, propagation par rhizomes.",
              "localisation_biome": "Marécages de Feslorin.",
              "usages_medicinaux": "Diurétiques à base de racine bouillie.",
              "usages_artisanaux": "Bâtiment sur pilotis et tressage batracien.",
              "usages_rituels": "Totems flottants pour chants aquatiques."
            },
            {
              "nom": "Trèfle doré des champs",
              "apparence": "Petite herbe à trois feuilles dorées, fleurs blanches parfumées.",
              "ressources_rares_sacrees": "Symbole chance et fertilité, rare hors Dralvaire.",
              "saison_floraison": "Printemps tardif à été.",
              "localisation_biome": "Bordures de routes et champs humides.",
              "usages_medicinaux": "Apaisant gastrique et purifiant du sang.",
              "usages_artisanaux": "Couronnes et motifs décoratifs.",
              "usages_rituels": "Offrandes dans les cérémonies d’union."
            }
          ]
        },
        {
          "type": "Rares_sacrees",
          "plantes": [
            {
              "nom": "Baie pigment rare",
              "apparence": "Baies rouges vives sur buisson épineux de 1 à 2 m.",
              "ressources_rares_sacrees": "Pigments stables et rares.",
              "saison_floraison": "Été à automne, cycle annuel.",
              "localisation_biome": "Collines de Korvalth.",
              "usages_medicinaux": "Jus vitalisant antioxydant.",
              "usages_artisanaux": "Teintures pour tissus et sceaux.",
              "usages_rituels": "Symboles protecteurs lors des rites forestiers."
            },
            {
              "nom": "Fleur perle aquatique",
              "apparence": "Large fleur blanche nacrée, tige submergée.",
              "ressources_rares_sacrees": "Source de perles rituelles et médicinales.",
              "saison_floraison": "Toute l’année, pic pendant les moussons.",
              "localisation_biome": "Lagons et marécages de Feslorin.",
              "usages_medicinaux": "Infusion sédative et relaxante.",
              "usages_artisanaux": "Bijoux et décorations bioluminescentes.",
              "usages_rituels": "Flottées dans les temples pour apaiser les esprits aquatiques."
            }
          ]
        }
      ]
    },
    {
      "nom": "Oriental",
      "flore": [
        {
          "type": "Normaux",
          "plantes": [
            {
              "nom": "Conifère de taïga",
              "apparence": "Épicéa haut de 40 m, écorce sombre et cônes pendants.",
              "ressources_rares_sacrees": "Bois souple utilisé partout dans la taïga.",
              "saison_floraison": "Printemps à automne.",
              "localisation_biome": "Taïga de Kerynth.",
              "usages_medicinaux": "Résine antiseptique pour blessures et brûlures.",
              "usages_artisanaux": "Charpentes et outils forestiers.",
              "usages_rituels": "Totems saisonniers gravés lors des migrations."
            },
            {
              "nom": "Buisson résineux sacré",
              "apparence": "Feuillage cireux et baies noires, 2 m de haut.",
              "ressources_rares_sacrees": "Résine hallucinogène concentrée.",
              "saison_floraison": "Printemps à été.",
              "localisation_biome": "Sous-canopée de Thyrvalen et Thulmar.",
              "usages_medicinaux": "Infusions visionnaires et purgatives.",
              "usages_artisanaux": "Encens aromatique et huiles spirituelles.",
              "usages_rituels": "Inhalé pour jugements chamaniques et pactes de vérité."
            }
          ]
        },
        {
          "type": "Rares_sacrees",
          "plantes": [
            {
              "nom": "Herbe de cime épicée",
              "apparence": "Tiges fines et fleurs dorées, bulbes profonds.",
              "ressources_rares_sacrees": "Épice sacrée, export stratégique.",
              "saison_floraison": "Été, récolte automnale.",
              "localisation_biome": "Montagnes d’Orraveth au-dessus de 2000 m.",
              "usages_medicinaux": "Stimulant respiratoire et circulatoire.",
              "usages_artisanaux": "Colorants dorés pour broderies nobles.",
              "usages_rituels": "Offertes aux dieux des cols et voyageurs."
            },
            {
              "nom": "Vigne cristalline des plateaux",
              "apparence": "Feuilles vitreuses, fruits translucides contenant lumière cosmique.",
              "ressources_rares_sacrees": "Verre céleste purifié par rites géants.",
              "saison_floraison": "Solstice, maturité tous les 4 ans.",
              "localisation_biome": "Plateaux de Vhorak.",
              "usages_medicinaux": "Tonique cosmique améliorant la clarté mentale.",
              "usages_artisanaux": "Verres et lentilles d’observation céleste.",
              "usages_rituels": "Consommée lors d’alignements stellaires."
            }
          ]
        }
      ]
    },
    {
      "nom": "Archipel méridional",
      "flore": [
        {
          "type": "Normaux",
          "plantes": [
            {
              "nom": "Palmier naval",
              "apparence": "Grand palmier de 25 m, fruits bruns et feuilles palmées.",
              "ressources_rares_sacrees": "Bois naval et fibres abondantes.",
              "saison_floraison": "Toute l’année sous climat tropical.",
              "localisation_biome": "Îles d’Islakarion.",
              "usages_medicinaux": "Eau de coco hydratante et antiseptique.",
              "usages_artisanaux": "Tissage de voiles et cordages.",
              "usages_rituels": "Noix flottées en offrandes marines."
            },
            {
              "nom": "Algue corallienne",
              "apparence": "Frondes rouges et souples de 1 à 2 m, texture gélatineuse.",
              "ressources_rares_sacrees": "Corail nutritif et pigmenté.",
              "saison_floraison": "Croissance maximale durant les moussons.",
              "localisation_biome": "Récifs submergés de Lago’Vernis.",
              "usages_medicinaux": "Anti-inflammatoire naturel.",
              "usages_artisanaux": "Pigments rouges pour tissus et encres.",
              "usages_rituels": "Jetée dans les courants pour bénir les marins."
            },
            {
              "nom": "Liane des vents",
              "apparence": "Plante grimpante à fleurs violettes, tiges spiralées jusqu’à 15 m.",
              "ressources_rares_sacrees": "Fibre souple utilisée pour voiles légères.",
              "saison_floraison": "Fin de saison sèche, repousse rapide.",
              "localisation_biome": "Forêts littorales de Venarith.",
              "usages_medicinaux": "Antiseptique cutané.",
              "usages_artisanaux": "Cordages et nœuds marins.",
              "usages_rituels": "Utilisée dans les serments des navigateurs."
            }
          ]
        },
        {
          "type": "Rares_sacrees",
          "plantes": [
            {
              "nom": "Fleur épicée tropicale",
              "apparence": "Orchidée orange à gousses noires parfumées, tiges rampantes.",
              "ressources_rares_sacrees": "Épices exportées à haute valeur.",
              "saison_floraison": "Saison des pluies, maturité en 6 mois.",
              "localisation_biome": "Jungles côtières d’Islakarion.",
              "usages_medicinaux": "Aphrodisiaque et relaxant.",
              "usages_artisanaux": "Parfums et huiles raffinées.",
              "usages_rituels": "Offrandes lors des prières solaires."
            },
            {
              "nom": "Herbe bioluminescente lagunaire",
              "apparence": "Feuilles flottantes émettant une lueur bleue sous la lune.",
              "ressources_rares_sacrees": "Teinte luminescente vénérée par les batraciens.",
              "saison_floraison": "Nuits de pleine lune durant les moussons.",
              "localisation_biome": "Lagunes de Venarith.",
              "usages_medicinaux": "Sédatif léger et calmant nerveux.",
              "usages_artisanaux": "Encres et tatouages lumineux.",
              "usages_rituels": "Illumine les bassins lors des méditations collectives."
            }
          ]
        }
      ]
    }
  ]
}
